openaivec/__init__.py
openaivec/_di.py
openaivec/_embeddings.py
openaivec/_log.py
openaivec/_model.py
openaivec/_prompt.py
openaivec/_provider.py
openaivec/_responses.py
openaivec/_serialize.py
openaivec/_util.py
openaivec/pandas_ext.py
openaivec/spark.py
openaivec/_cache/__init__.py
openaivec/_cache/optimize.py
openaivec/_cache/proxy.py
openaivec/_schema/__init__.py
openaivec/_schema/infer.py
openaivec/_schema/spec.py
openaivec/task/__init__.py
openaivec/task/customer_support/__init__.py
openaivec/task/customer_support/customer_sentiment.py
openaivec/task/customer_support/inquiry_classification.py
openaivec/task/customer_support/inquiry_summary.py
openaivec/task/customer_support/intent_analysis.py
openaivec/task/customer_support/response_suggestion.py
openaivec/task/customer_support/urgency_analysis.py
openaivec/task/nlp/__init__.py
openaivec/task/nlp/dependency_parsing.py
openaivec/task/nlp/keyword_extraction.py
openaivec/task/nlp/morphological_analysis.py
openaivec/task/nlp/named_entity_recognition.py
openaivec/task/nlp/sentiment_analysis.py
openaivec/task/nlp/translation.py
openaivec/task/table/__init__.py
openaivec/task/table/fillna.py
openaivec-1.0.10.dist-info/METADATA
openaivec-1.0.10.dist-info/WHEEL
openaivec-1.0.10.dist-info/licenses/LICENSE
openaivec-1.0.10.dist-info/RECORD
