Metadata-Version: 2.4
Name: openaivec
Version: 1.0.10
Summary: Generative mutation for tabular calculation
Project-URL: Homepage, https://microsoft.github.io/openaivec/
Project-URL: Repository, https://github.com/microsoft/openaivec
Author-email: Hiroki Mizukami <hmizukami@microsoft.com>
License: MIT
License-File: LICENSE
Keywords: llm,openai,openai-api,openai-python,pandas,pyspark
Classifier: Development Status :: 4 - Beta
Classifier: Intended Audience :: Developers
Classifier: License :: OSI Approved :: MIT License
Classifier: Programming Language :: Python :: 3.10
Classifier: Programming Language :: Python :: 3.11
Classifier: Programming Language :: Python :: 3.12
Requires-Python: >=3.10
Requires-Dist: ipywidgets>=8.1.7
Requires-Dist: openai>=1.74.0
Requires-Dist: pandas>=2.2.3
Requires-Dist: tiktoken>=0.9.0
Requires-Dist: tqdm>=4.67.1
Provides-Extra: spark
Requires-Dist: pyspark>=3.5.5; extra == 'spark'
